calibcam/__init__.py
calibcam/__main__.py
calibcam/calibrator_opts.py
calibcam/camcalibrator.py
calibcam/camfunctions.py
calibcam/camfunctions_ag.py
calibcam/compatibility.py
calibcam/detection.py
calibcam/exceptions.py
calibcam/helper.py
calibcam/helper_4pi
calibcam/helper_ag.py
calibcam/optimization.py
calibcam/pose_estimation.py
calibcam/single_camcalibration.py
calibcam/yaml_helper.py
calibcam/repro/__init__.py
calibcam/repro/optfunctions.py
calibcam/repro/optfunctions_ag.py
bbo_calibcam-4.0.1.dist-info/METADATA
bbo_calibcam-4.0.1.dist-info/WHEEL
bbo_calibcam-4.0.1.dist-info/licenses/LICENSE
bbo_calibcam-4.0.1.dist-info/RECORD
