Metadata-Version: 2.3
Name: bbo-calibcam
Version: 4.0.1
Summary: Calibrate intrinsic and extrinsic parameters of cameras with charuco boards
Project-URL: Homepage, https://github.com/bbo-lab/calibcam
Author-email: "BBO-lab @ caesar" <kay-michael.voit@mpinb.mpg.de>
License: LGPL-3.0-or-later
Classifier: License :: OSI Approved :: GNU Lesser General Public License v2 or later (LGPLv2+)
Classifier: Programming Language :: Python :: 3.10
Requires-Dist: bbo-bbo
Requires-Dist: bbo-calibcamlib
Requires-Dist: bbo-ccvtools
Requires-Dist: bbo-svidreader
Requires-Dist: imageio
Requires-Dist: jax
Requires-Dist: jaxlib
Requires-Dist: numpy
Requires-Dist: pyyaml
Requires-Dist: scipy
